aiogram_mvc/__init__.py
aiogram_mvc/config.py
aiogram_mvc/controller/__init__.py
aiogram_mvc/middleware/__init__.py
aiogram_mvc/middleware/callback.py
aiogram_mvc/middleware/exception.py
aiogram_mvc/middleware/middleware.py
aiogram_mvc/model/__init__.py
aiogram_mvc/model/call_data.py
aiogram_mvc/model/deep_link.py
aiogram_mvc/view/__init__.py
aiogram_mvc/view/base.py
aiogram_mvc/view/call.py
aiogram_mvc/view/exception.py
aiogram_mvc/view/inline.py
aiogram_mvc/view/message.py
aiogram_mvc/view/poll.py
aiogram_mvc-0.1.1597519517.dist-info/METADATA
aiogram_mvc-0.1.1597519517.dist-info/WHEEL
aiogram_mvc-0.1.1597519517.dist-info/top_level.txt
aiogram_mvc-0.1.1597519517.dist-info/RECORD
